tqdm-stubs/METADATA.toml
tqdm-stubs/__init__.pyi
tqdm-stubs/_dist_ver.pyi
tqdm-stubs/_main.pyi
tqdm-stubs/_monitor.pyi
tqdm-stubs/_tqdm.pyi
tqdm-stubs/_tqdm_gui.pyi
tqdm-stubs/_tqdm_notebook.pyi
tqdm-stubs/_tqdm_pandas.pyi
tqdm-stubs/_utils.pyi
tqdm-stubs/asyncio.pyi
tqdm-stubs/auto.pyi
tqdm-stubs/autonotebook.pyi
tqdm-stubs/cli.pyi
tqdm-stubs/dask.pyi
tqdm-stubs/gui.pyi
tqdm-stubs/keras.pyi
tqdm-stubs/notebook.pyi
tqdm-stubs/py.typed
tqdm-stubs/rich.pyi
tqdm-stubs/std.pyi
tqdm-stubs/tk.pyi
tqdm-stubs/utils.pyi
tqdm-stubs/version.pyi
tqdm-stubs/contrib/__init__.pyi
tqdm-stubs/contrib/bells.pyi
tqdm-stubs/contrib/concurrent.pyi
tqdm-stubs/contrib/discord.pyi
tqdm-stubs/contrib/itertools.pyi
tqdm-stubs/contrib/logging.pyi
tqdm-stubs/contrib/slack.pyi
tqdm-stubs/contrib/telegram.pyi
tqdm-stubs/contrib/utils_worker.pyi
types_tqdm-4.67.0.20250513.dist-info/licenses/LICENSE
types_tqdm-4.67.0.20250513.dist-info/METADATA
types_tqdm-4.67.0.20250513.dist-info/WHEEL
types_tqdm-4.67.0.20250513.dist-info/top_level.txt
types_tqdm-4.67.0.20250513.dist-info/RECORD
